tweet_downloader/__init__.py
tweet_downloader/tweet_dl.py
tweets_dl-0.1.1.dist-info/DESCRIPTION.rst
tweets_dl-0.1.1.dist-info/METADATA
tweets_dl-0.1.1.dist-info/RECORD
tweets_dl-0.1.1.dist-info/WHEEL
tweets_dl-0.1.1.dist-info/entry_points.txt
tweets_dl-0.1.1.dist-info/metadata.json
tweets_dl-0.1.1.dist-info/top_level.txt
