Metadata-Version: 2.0
Name: tweets-dl
Version: 0.1.1
Summary: UNKNOWN
Home-page: https://github.com/Vaishali-Garg/tweet-downloader
Author: Vaishali Garg
Author-email: vaishaligarg@gmail.com
License: UNKNOWN
Platform: UNKNOWN
Requires-Dist: requests
